Workbook

Sheet Inputs
A1: 249Souq — Bukhoor cost & price model (Oct 2026)
A2: Blue = input you can change. Everything else is a formula. Yellow = main decision cell.
A3: Item | B3: Value | C3: Source / note
A4: Production cost per jar (raw materials + jar + bag) | B4: 14.6 | C4: Source: 4 Sep 2026 cost summary (AED 280 raw materials per batch of 24 jars + AED 2.33 jar + AED 0.60 bag). Estimate shared by the maker; khomra was NOT in it (she used her own stock).
A5: Khomra: price per bottle (AED) | B5: 200 | C5: Stated by Salwa (Oct 2026) — maker now buys khomra instead of using her own stock.
A6: Big bottles of bukhoor made from 1 khomra bottle | B6: 3 | C6: Stated by Salwa.
A7: Small jars per big bottle | B7: 46 | C7: Stated by Salwa (roughly).
A8: Jars per khomra bottle | B8: =B6*B7 -> 138 | C8: Formula
A9: Khomra cost per jar | B9: =B5/B8 -> 1.4492754 | C9: Formula
A10: NEW full production cost per jar | B10: =B4+B9 -> 16.049275 | C10: Formula = old cost + khomra
A11: Cost price Salwa pays the maker per jar (AED) | B11: 40 | C11: Stated: stays AED 40, includes everything.
A12: Maker's profit per jar (AED) | B12: =B11-B10 -> 23.950725 | C12: Formula
A13: Maker's profit % of her price | B13: =B12/B11 -> 0.59876812 | C13: Formula
A14: Courier cost per parcel (AED) | B14: 15 | C14: Sheet 4 of uae_gcc_courier_shortlist.xlsx (IQ Fulfillment, up to 5kg).
A15: Delivery fee charged to customer (AED) | B15: 20 | C15: Fixed AED 20 — Sheet 4.
A16: Courier monthly minimum billing (AED) | B16: 500 | C16: Sheet 4 — confirm with IQF whether it applies from month 1.
A17: Stripe fee % | B17: 0.029 | C17: Estimate (2.9% + AED 1) — also used in Sheet 4; check your Stripe account.
A18: Stripe fixed fee per payment (AED) | B18: 1 | C18: Estimate.
A19: Retail price per jar being tested (AED) | B19: 75 | C19: DECISION CELL — change this to see "Orders per month" update.

Sheet Price options
A1: Price options per jar (AED) — what you earn after Stripe fee and courier
A2: Single order = customer pays jar + AED 20 delivery. Buy-2 = 2 jars, free shipping (you pay the courier). Assumes courier minimum already covered (30+ orders/month).
A4: Retail price per jar | B4: Product margin (AED) | C4: Product margin % | D4: Customer pays (1 jar + delivery) | E4: Stripe fee | F4: Delivery margin (fee − courier) | G4: NET per 1-jar order | H4: Buy-2 price (free shipping) | I4: Stripe fee on buy-2 | J4: NET per buy-2 order | K4: NET per jar in buy-2
A5: 65 | B5: =A5-Inputs!$B$11 -> 25 | C5: =B5/A5 -> 0.38461538 | D5: =A5+Inputs!$B$15 -> 85 | E5: =D5*Inputs!$B$17+Inputs!$B$18 -> 3.465 | F5: =Inputs!$B$15-Inputs!$B$14 -> 5 | G5: =B5+F5-E5 -> 26.535 | H5: =2*A5 -> 130 | I5: =H5*Inputs!$B$17+Inputs!$B$18 -> 4.77 | J5: =2*B5-Inputs!$B$14-I5 -> 30.23 | K5: =J5/2 -> 15.115
A6: 70 | B6: =A6-Inputs!$B$11 -> 30 | C6: =B6/A6 -> 0.42857143 | D6: =A6+Inputs!$B$15 -> 90 | E6: =D6*Inputs!$B$17+Inputs!$B$18 -> 3.61 | F6: =Inputs!$B$15-Inputs!$B$14 -> 5 | G6: =B6+F6-E6 -> 31.39 | H6: =2*A6 -> 140 | I6: =H6*Inputs!$B$17+Inputs!$B$18 -> 5.06 | J6: =2*B6-Inputs!$B$14-I6 -> 39.94 | K6: =J6/2 -> 19.97
A7: 75 | B7: =A7-Inputs!$B$11 -> 35 | C7: =B7/A7 -> 0.46666667 | D7: =A7+Inputs!$B$15 -> 95 | E7: =D7*Inputs!$B$17+Inputs!$B$18 -> 3.755 | F7: =Inputs!$B$15-Inputs!$B$14 -> 5 | G7: =B7+F7-E7 -> 36.245 | H7: =2*A7 -> 150 | I7: =H7*Inputs!$B$17+Inputs!$B$18 -> 5.35 | J7: =2*B7-Inputs!$B$14-I7 -> 49.65 | K7: =J7/2 -> 24.825
A8: 80 | B8: =A8-Inputs!$B$11 -> 40 | C8: =B8/A8 -> 0.5 | D8: =A8+Inputs!$B$15 -> 100 | E8: =D8*Inputs!$B$17+Inputs!$B$18 -> 3.9 | F8: =Inputs!$B$15-Inputs!$B$14 -> 5 | G8: =B8+F8-E8 -> 41.1 | H8: =2*A8 -> 160 | I8: =H8*Inputs!$B$17+Inputs!$B$18 -> 5.64 | J8: =2*B8-Inputs!$B$14-I8 -> 59.36 | K8: =J8/2 -> 29.68
A9: 85 | B9: =A9-Inputs!$B$11 -> 45 | C9: =B9/A9 -> 0.52941176 | D9: =A9+Inputs!$B$15 -> 105 | E9: =D9*Inputs!$B$17+Inputs!$B$18 -> 4.045 | F9: =Inputs!$B$15-Inputs!$B$14 -> 5 | G9: =B9+F9-E9 -> 45.955 | H9: =2*A9 -> 170 | I9: =H9*Inputs!$B$17+Inputs!$B$18 -> 5.93 | J9: =2*B9-Inputs!$B$14-I9 -> 69.07 | K9: =J9/2 -> 34.535
A10: 90 | B10: =A10-Inputs!$B$11 -> 50 | C10: =B10/A10 -> 0.55555556 | D10: =A10+Inputs!$B$15 -> 110 | E10: =D10*Inputs!$B$17+Inputs!$B$18 -> 4.19 | F10: =Inputs!$B$15-Inputs!$B$14 -> 5 | G10: =B10+F10-E10 -> 50.81 | H10: =2*A10 -> 180 | I10: =H10*Inputs!$B$17+Inputs!$B$18 -> 6.22 | J10: =2*B10-Inputs!$B$14-I10 -> 78.78 | K10: =J10/2 -> 39.39
A12: Reading this:
A13: • Khomra adds only about AED 1.45 per jar to production cost. The maker's cost price to you can stay AED 40 and she still keeps about 60%.
A14: • The price decision is about YOUR margin, not about the khomra. Compare the NET columns; the higher price leaves more room for promos (free roll-on, buy-2 shipping).
A15: • Tabby fees (if you use it) are NOT included — check your Tabby merchant rate and subtract it on Tabby orders.

Sheet Orders per month
A1: Monthly profit at the price in Inputs!B19 (1-jar orders, AED 20 delivery)
A2: Retail price tested: | B2: =Inputs!B19 -> 75
A4: Orders / month | B4: Product margin | C4: Delivery revenue | D4: Courier cost (min applies) | E4: Stripe fees | F4: NET profit | G4: NET per order
A5: 5 | B5: =A5*($B$2-Inputs!$B$11) -> 175 | C5: =A5*Inputs!$B$15 -> 100 | D5: =MAX(A5*Inputs!$B$14,Inputs!$B$16) -> 500 | E5: =A5*(($B$2+Inputs!$B$15)*Inputs!$B$17+Inputs!$B$18) -> 18.775 | F5: =B5+C5-D5-E5 -> -243.775 | G5: =F5/A5 -> -48.755
A6: 10 | B6: =A6*($B$2-Inputs!$B$11) -> 350 | C6: =A6*Inputs!$B$15 -> 200 | D6: =MAX(A6*Inputs!$B$14,Inputs!$B$16) -> 500 | E6: =A6*(($B$2+Inputs!$B$15)*Inputs!$B$17+Inputs!$B$18) -> 37.55 | F6: =B6+C6-D6-E6 -> 12.45 | G6: =F6/A6 -> 1.245
A7: 15 | B7: =A7*($B$2-Inputs!$B$11) -> 525 | C7: =A7*Inputs!$B$15 -> 300 | D7: =MAX(A7*Inputs!$B$14,Inputs!$B$16) -> 500 | E7: =A7*(($B$2+Inputs!$B$15)*Inputs!$B$17+Inputs!$B$18) -> 56.325 | F7: =B7+C7-D7-E7 -> 268.675 | G7: =F7/A7 -> 17.911667
A8: 25 | B8: =A8*($B$2-Inputs!$B$11) -> 875 | C8: =A8*Inputs!$B$15 -> 500 | D8: =MAX(A8*Inputs!$B$14,Inputs!$B$16) -> 500 | E8: =A8*(($B$2+Inputs!$B$15)*Inputs!$B$17+Inputs!$B$18) -> 93.875 | F8: =B8+C8-D8-E8 -> 781.125 | G8: =F8/A8 -> 31.245
A9: 34 | B9: =A9*($B$2-Inputs!$B$11) -> 1190 | C9: =A9*Inputs!$B$15 -> 680 | D9: =MAX(A9*Inputs!$B$14,Inputs!$B$16) -> 510 | E9: =A9*(($B$2+Inputs!$B$15)*Inputs!$B$17+Inputs!$B$18) -> 127.67 | F9: =B9+C9-D9-E9 -> 1232.33 | G9: =F9/A9 -> 36.245
A10: 50 | B10: =A10*($B$2-Inputs!$B$11) -> 1750 | C10: =A10*Inputs!$B$15 -> 1000 | D10: =MAX(A10*Inputs!$B$14,Inputs!$B$16) -> 750 | E10: =A10*(($B$2+Inputs!$B$15)*Inputs!$B$17+Inputs!$B$18) -> 187.75 | F10: =B10+C10-D10-E10 -> 1812.25 | G10: =F10/A10 -> 36.245
A11: 75 | B11: =A11*($B$2-Inputs!$B$11) -> 2625 | C11: =A11*Inputs!$B$15 -> 1500 | D11: =MAX(A11*Inputs!$B$14,Inputs!$B$16) -> 1125 | E11: =A11*(($B$2+Inputs!$B$15)*Inputs!$B$17+Inputs!$B$18) -> 281.625 | F11: =B11+C11-D11-E11 -> 2718.375 | G11: =F11/A11 -> 36.245
A12: 100 | B12: =A12*($B$2-Inputs!$B$11) -> 3500 | C12: =A12*Inputs!$B$15 -> 2000 | D12: =MAX(A12*Inputs!$B$14,Inputs!$B$16) -> 1500 | E12: =A12*(($B$2+Inputs!$B$15)*Inputs!$B$17+Inputs!$B$18) -> 375.5 | F12: =B12+C12-D12-E12 -> 3624.5 | G12: =F12/A12 -> 36.245
A14: Note: the AED 500 courier minimum makes low-volume months look worse; confirm with IQ Fulfillment whether it applies from month 1.
